mcp_browser/__init__.py
mcp_browser/_version.py
mcp_browser/dev_runner.py
mcp_browser/cli/__init__.py
mcp_browser/cli/main.py
mcp_browser/cli/commands/__init__.py
mcp_browser/cli/commands/browser.py
mcp_browser/cli/commands/browser_refactored.py
mcp_browser/cli/commands/connect.py
mcp_browser/cli/commands/demo.py
mcp_browser/cli/commands/doctor.py
mcp_browser/cli/commands/extension.py
mcp_browser/cli/commands/init.py
mcp_browser/cli/commands/install.py
mcp_browser/cli/commands/install_legacy.py
mcp_browser/cli/commands/quickstart.py
mcp_browser/cli/commands/setup.py
mcp_browser/cli/commands/start.py
mcp_browser/cli/commands/status.py
mcp_browser/cli/commands/stop.py
mcp_browser/cli/commands/tutorial.py
mcp_browser/cli/utils/__init__.py
mcp_browser/cli/utils/browser_client.py
mcp_browser/cli/utils/daemon.py
mcp_browser/cli/utils/display.py
mcp_browser/cli/utils/extension.py
mcp_browser/cli/utils/server.py
mcp_browser/cli/utils/validation.py
mcp_browser/container/__init__.py
mcp_browser/container/service_container.py
mcp_browser/extension/Readability.js
mcp_browser/extension/background-enhanced.js
mcp_browser/extension/background.js
mcp_browser/extension/content.js
mcp_browser/extension/create_icons.html
mcp_browser/extension/demo.html
mcp_browser/extension/icon-128.png
mcp_browser/extension/icon-16.png
mcp_browser/extension/icon-48.png
mcp_browser/extension/manifest.json
mcp_browser/extension/popup-enhanced.html
mcp_browser/extension/popup-enhanced.js
mcp_browser/extension/popup.html
mcp_browser/extension/popup.js
mcp_browser/extensions/README.md
mcp_browser/extensions/chrome/Readability.js
mcp_browser/extensions/chrome/background-enhanced.js
mcp_browser/extensions/chrome/content.js
mcp_browser/extensions/chrome/manifest.json
mcp_browser/extensions/chrome/popup-enhanced.html
mcp_browser/extensions/chrome/popup-enhanced.js
mcp_browser/extensions/chrome/icons/icon128-green.png
mcp_browser/extensions/chrome/icons/icon128-outline.png
mcp_browser-2.2.63.dist-info/licenses/LICENSE
mcp_browser-2.2.63.dist-info/METADATA
mcp_browser-2.2.63.dist-info/WHEEL
mcp_browser-2.2.63.dist-info/entry_points.txt
mcp_browser-2.2.63.dist-info/top_level.txt
mcp_browser-2.2.63.dist-info/RECORD
