Metadata-Version: 2.4
Name: mcp-browser
Version: 2.2.63
Summary: Browser control and console log capture for AI coding assistants via MCP
Home-page: https://github.com/browserpymcp/mcp-browser
Author: Bob Matsuoka
Author-email: Bob Matsuoka <bob@matsuoka.com>
License: MIT
Project-URL: Homepage, https://github.com/browserpymcp/mcp-browser
Project-URL: Documentation, https://docs.browserpymcp.dev
Project-URL: Repository, https://github.com/browserpymcp/mcp-browser
Project-URL: Issues, https://github.com/browserpymcp/mcp-browser/issues
Classifier: Development Status :: 4 - Beta
Classifier: Intended Audience :: Developers
Classifier: License :: OSI Approved :: MIT License
Classifier: Programming Language :: Python :: 3
Classifier: Programming Language :: Python :: 3.10
Classifier: Programming Language :: Python :: 3.11
Classifier: Programming Language :: Python :: 3.12
Classifier: Topic :: Software Development :: Libraries
Classifier: Topic :: Internet :: WWW/HTTP :: Browsers
Requires-Python: >=3.10
License-File: LICENSE
Requires-Dist: mcp>=0.1.0
Requires-Dist: websockets>=11.0
Requires-Dist: aiofiles>=23.0.0
Requires-Dist: aiohttp>=3.9.0
Requires-Dist: click>=8.1.0
Requires-Dist: rich>=13.7.0
Requires-Dist: py-mcp-installer>=0.1.4
Provides-Extra: dev
Requires-Dist: pytest>=7.0.0; extra == "dev"
Requires-Dist: pytest-asyncio>=0.21.0; extra == "dev"
Requires-Dist: pytest-cov>=4.0.0; extra == "dev"
Requires-Dist: black>=23.0.0; extra == "dev"
Requires-Dist: mypy>=1.0.0; extra == "dev"
Requires-Dist: ruff>=0.1.0; extra == "dev"
Dynamic: author
Dynamic: home-page
Dynamic: license-file
Dynamic: requires-python
